src/__init__.py
src/__main__.py
src/__version__.py
adventofcode_initializer-1.0.5.dist-info/COPYING
adventofcode_initializer-1.0.5.dist-info/METADATA
adventofcode_initializer-1.0.5.dist-info/WHEEL
adventofcode_initializer-1.0.5.dist-info/entry_points.txt
adventofcode_initializer-1.0.5.dist-info/top_level.txt
adventofcode_initializer-1.0.5.dist-info/RECORD
