Metadata-Version: 2.1
Name: adventofcode-initializer
Version: 1.0.5
Summary: Download Advent of Code problems as markdown files and also its inputs
Home-page: https://github.com/Serms1999/advent-initializer
Download-URL: https://github.com/Serms1999/advent-initializer/releases/tag/v1.0.5
Author: Sergio Marín Sánchez
Author-email: serms1999@gmail.com
License: GNU GENERAL PUBLIC LICENSE
Keywords: advent-of-code,development,markdown
Classifier: Programming Language :: Python :: 3
Classifier: License :: OSI Approved :: GNU General Public License v3 (GPLv3)
Classifier: Operating System :: OS Independent
Classifier: Environment :: Console
Classifier: Natural Language :: English
Requires-Python: >=3.6
License-File: COPYING
Requires-Dist: beautifulsoup4 (==4.11.1)
Requires-Dist: markdownify (==0.11.6)
Requires-Dist: requests (==2.28.1)
Requires-Dist: setuptools (==65.5.0)
